Fingilish/__init__.py
fingilish-1.0.1.dist-info/licenses/LICENSE
fingilish-1.0.1.dist-info/METADATA
fingilish-1.0.1.dist-info/WHEEL
fingilish-1.0.1.dist-info/top_level.txt
fingilish-1.0.1.dist-info/RECORD
