Metadata-Version: 2.4
Name: Fingilish
Version: 1.0.1
Summary: A python library for iranian people to code better and easier.
Home-page: https://github.com/soodi592/Finglish
Author: soodi592
Author-email: soodi.592.ali@gmail.com
License: MIT
License-File: LICENSE
Dynamic: author
Dynamic: author-email
Dynamic: description
Dynamic: description-content-type
Dynamic: home-page
Dynamic: license
Dynamic: license-file
Dynamic: summary
